{"chapter" : 114 , "title_am" : "አል-ናስ" , "title_ar" : "الناس" , "count" : "6" , "quran" : [ 
{ "verse" : 0 , "ar" : "بِسۡمِ ٱللَّهِ ٱلرَّحۡمَـٰنِ ٱلرَّحِیمِ" , "tr" : "በአላህ ስም እጅግ በጣም ሩኅሩህ በጣም አዛኝ በኾነው፡፡" },
{ "verse" : 1 , "ar" : "قُلۡ أَعُوذُ بِرَبِّ ٱلنَّاسِ" , "tr" : "በል «በሰዎች ፈጣሪ እጠበቃለሁ፡፡" },
{ "verse" : 2 , "ar" : "مَلِكِ ٱلنَّاسِ" , "tr" : "«የሰዎች ሁሉ ንጉሥ በኾነው፡፡" },
{ "verse" : 3 , "ar" : "إِلَـٰهِ ٱلنَّاسِ" , "tr" : "«የሰዎች አምላክ በኾነው፡፡" },
{ "verse" : 4 , "ar" : "مِن شَرِّ ٱلۡوَسۡوَاسِ ٱلۡخَنَّاسِ" , "tr" : "«ብቅ እልም ባይ ከኾነው ጎትጓች (ሰይጣን) ክፋት፡፡" },
{ "verse" : 5 , "ar" : "ٱلَّذِی یُوَسۡوِسُ فِی صُدُورِ ٱلنَّاسِ" , "tr" : "«ከዚያ በሰዎች ልቦች ውስጥ የሚጎተጉት ከኾነው፡፡" },
{ "verse" : 6 , "ar" : "مِنَ ٱلۡجِنَّةِ وَٱلنَّاسِ" , "tr" : "«ከጋኔኖችም ከሰዎችም (ሰይጣናት እጠበቃለሁ በል)፡፡»" }
] }